{
  "name": "津村 尚史",
  "title": "代表取締役社長",
  "appointment_info": "2021年5月",
  "source_url": "https://www.j-tec.co.jp/company-profile/officer/",
  "photos_saved": [
    "photo_01.jpg",
    "photo_02.jpg",
    "photo_03.jpg",
    "photo_04.jpg"
  ],
  "photo_count": 4,
  "photo_saved": true,
  "stock_price_at_appointment": {
    "date": "2021-05-01",
    "open_on_date": 2910.0,
    "close_on_date": 2870.0,
    "high_on_date": 2968.0,
    "low_on_date": 2858.0,
    "trading_date": "2021-04-21",
    "currency": "JPY"
  },
  "open_at_appointment": 2910.0
}