{
  "name": "藤原　弘之",
  "title": "代表取締役社長",
  "appointment_info": "2025年10月",
  "source_url": "https://www.shinagawa.co.jp/profile/message.html",
  "photos_saved": [
    "photo_01.jpg"
  ],
  "photo_count": 1,
  "photo_saved": true,
  "stock_price_at_appointment": {
    "date": "2025-10-01",
    "open_on_date": 1863.49,
    "close_on_date": 1865.44,
    "high_on_date": 1870.33,
    "low_on_date": 1863.49,
    "trading_date": "2025-09-22",
    "currency": "JPY"
  },
  "open_at_appointment": 1863.49
}